{
    "tmax": 300.0,
    "plots": [
        {
            "I": 8,
            "V0": -70,
            "model": "HH_standard"
        },
        {
            "I": 8,
            "V0": -70,
            "model": "HH_aprox_1"
        },
        {
            "I": 8,
            "V0": -70,
            "model": "HH_aprox_2",
            "k": 0.7
        },
        {
            "I": 8,
            "V0": -70,
            "model": "HH_aprox_2",
            "k": 1.0
        },
        {
            "I": 8,
            "V0": -70,
            "model": "HH_aprox_2",
            "k": 1.4
        }
    ]
}